o11y/__init__.py
o11y/_internal/__init__.py
o11y/_internal/client.py
o11y/_internal/o11y_go.py
o11y/_internal/util/validate_url.py
o11y/exported/__init__.py
o11y/exported/finish.py
o11y/exported/init.py
o11y/exported/log.py
o11y/exported/update.py
o11y/_internal/o11y-go
o11y-0.1.2.dist-info/METADATA
o11y-0.1.2.dist-info/WHEEL
o11y-0.1.2.dist-info/licenses/LICENSE
o11y-0.1.2.dist-info/RECORD
